Metadata-Version: 2.1
Name: function-optimization
Version: 0.3.1
Summary: Optimize functions.Newton and Gradient descent methods
Home-page: UNKNOWN
Author: Mark Eltsefon
Author-email: meltsefon1@gmail.com
License: UNKNOWN
Platform: UNKNOWN
